<?xml version = '1.0' encoding = 'UTF-8'?>
<FKIndexAssociation class="oracle.dbtools.crest.model.design.relational.FKIndexAssociation" id="FAE34520-27DE-C1EF-10A4-A5A1708E6341" directorySegmentName="seg_0" name="FK_TCO_TSC">
<createdBy>Scott</createdBy>
<createdTime>2012-02-29 13:37:33 UTC</createdTime>
<ownerDesignName>Population Statistics Reference</ownerDesignName>
<containerWithKeyObject>37AE6DBD-854A-965D-E35D-88EAEB37DA3F</containerWithKeyObject>
<deleteRule>RESTRICT</deleteRule>
<localFKIndex>90F83945-A2E8-E103-A54F-26A732EB7BF6</localFKIndex>
<keyObject>2D4A2722-1B60-53EE-342D-6DEC30673200</keyObject>
<mandatory>true</mandatory>
<transferable>true</transferable>
</FKIndexAssociation>