<?xml version = '1.0' encoding = 'UTF-8'?>
<Table class="oracle.dbtools.crest.model.design.relational.Table" id="0DA3F6B4-8518-F552-7B4C-1ADAA9907CC6" directorySegmentName="seg_0" name="T_STATISTICS">
<createdBy>Scott</createdBy>
<createdTime>2011-10-26 10:37:49 UTC</createdTime>
<generatorID>4322327C-468C-22CC-2C1F-D48612BD13EC</generatorID>
<ownerDesignName>Population Statistics Reference</ownerDesignName>
<pkName>PK_STATISTIC</pkName>
<typeID>1</typeID>
<abbreviation>STC</abbreviation>
<fonts>
<FontObject class="oracle.dbtools.crest.model.design.FontObjectWr">
<foType>Title</foType>
<fontStyle>1</fontStyle>
<colorRGB>-16776961</colorRGB>
</FontObject>
<FontObject class="oracle.dbtools.crest.model.design.FontObjectWr">
<foType>Column</foType>
<colorRGB>-16777216</colorRGB>
</FontObject>
<FontObject class="oracle.dbtools.crest.model.design.FontObjectWr">
<foType>Datatype</foType>
<colorRGB>-16744448</colorRGB>
</FontObject>
<FontObject class="oracle.dbtools.crest.model.design.FontObjectWr">
<foType>PK Element</foType>
<colorRGB>-16776961</colorRGB>
</FontObject>
<FontObject class="oracle.dbtools.crest.model.design.FontObjectWr">
<foType>FK Element</foType>
<colorRGB>-16777216</colorRGB>
</FontObject>
<FontObject class="oracle.dbtools.crest.model.design.FontObjectWr">
<foType>UK Element</foType>
<colorRGB>-16776961</colorRGB>
</FontObject>
<FontObject class="oracle.dbtools.crest.model.design.FontObjectWr">
<foType>Not Null</foType>
<colorRGB>-65536</colorRGB>
</FontObject>
<FontObject class="oracle.dbtools.crest.model.design.FontObjectWr">
<foType>Key</foType>
<colorRGB>-16777216</colorRGB>
</FontObject>
</fonts>
<columns>
<Column class="oracle.dbtools.crest.model.design.relational.Column" name="ID" id="9DBA208D-CE95-1051-9F37-5BC61B6244C2">
<createdBy>Scott</createdBy>
<createdTime>2011-10-26 13:44:08 UTC</createdTime>
<ownerDesignName>Population Statistics Reference</ownerDesignName>
<constraintName>CH_STC_ID</constraintName>
<use>0</use>
<logicalDatatype>LOGDT011</logicalDatatype>
<domain>7902D946-5C37-B380-3248-80191020E6EF</domain>
<autoIncrementColumn>true</autoIncrementColumn>
<autoIncrementCycle>false</autoIncrementCycle>
<autoIncrementDisableCache>false</autoIncrementDisableCache>
<autoIncrementOrder>false</autoIncrementOrder>
<autoIncrementSequenceName>STC_SEQ</autoIncrementSequenceName>
<autoIncrementGenerateTrigger>false</autoIncrementGenerateTrigger>
</Column>
<Column class="oracle.dbtools.crest.model.design.relational.Column" name="PSG_ID" id="29CC72C1-8AEF-0D91-DDA5-FEF62A8456E7">
<createdBy>Scott</createdBy>
<createdTime>2012-09-05 15:07:25 UTC</createdTime>
<ownerDesignName>Population Statistics Reference</ownerDesignName>
<useDomainConstraints>false</useDomainConstraints>
<use>0</use>
<logicalDatatype>LOGDT011</logicalDatatype>
<domain>7902D946-5C37-B380-3248-80191020E6EF</domain>
<delegate>AEB0255B-BEA7-2999-B8A3-E334130E7989</delegate>
<previousColumn>false</previousColumn>
<autoIncrementCycle>false</autoIncrementCycle>
<associations>
<colAssociation fkAssociation="679FF3B5-93E8-EC20-42A1-09DB68725FEF" referredColumn="AEB0255B-BEA7-2999-B8A3-E334130E7989"/>
</associations>
</Column>
<Column class="oracle.dbtools.crest.model.design.relational.Column" name="STCT_CODE" id="7F16941E-0450-0982-F034-DF334E5BB70B">
<createdBy>Scott</createdBy>
<createdTime>2011-10-26 10:37:49 UTC</createdTime>
<generatorID>463835AA-AD85-7E5C-985E-BB9C3766C438</generatorID>
<ownerDesignName>Population Statistics Reference</ownerDesignName>
<useDomainConstraints>false</useDomainConstraints>
<use>0</use>
<logicalDatatype>LOGDT024</logicalDatatype>
<domain>70D4DB78-A0D4-8ECC-7713-712D57DFBB60</domain>
<delegate>EB338200-AC8F-6607-A8D2-6B97B7122060</delegate>
<previousColumn>false</previousColumn>
<associations>
<colAssociation fkAssociation="640305E8-8463-4BE4-5868-5DEA0C7BB92C" referredColumn="EB338200-AC8F-6607-A8D2-6B97B7122060"/>
</associations>
</Column>
<Column class="oracle.dbtools.crest.model.design.relational.Column" name="PER_ID" id="94054760-D809-F88B-4EEE-0DACCFC1F534">
<createdBy>Scott</createdBy>
<createdTime>2012-03-29 11:59:41 UTC</createdTime>
<ownerDesignName>Population Statistics Reference</ownerDesignName>
<useDomainConstraints>false</useDomainConstraints>
<use>0</use>
<logicalDatatype>LOGDT011</logicalDatatype>
<domain>7902D946-5C37-B380-3248-80191020E6EF</domain>
<delegate>A60499DA-C2F4-680A-2B87-78D396A5374B</delegate>
<autoIncrementCycle>false</autoIncrementCycle>
<associations>
<colAssociation fkAssociation="A569C6E7-519A-E8CE-A5F3-1C65EBF08D06" referredColumn="A60499DA-C2F4-680A-2B87-78D396A5374B"/>
</associations>
</Column>
<Column class="oracle.dbtools.crest.model.design.relational.Column" name="SEX_CODE" id="12403EFF-B965-DC85-DF84-4FD6950E185D">
<createdBy>Scott</createdBy>
<createdTime>2011-10-26 10:37:49 UTC</createdTime>
<generatorID>B0E52CCC-AF80-FA06-9233-6DE27055D53B</generatorID>
<ownerDesignName>Population Statistics Reference</ownerDesignName>
<nullsAllowed>true</nullsAllowed>
<useDomainConstraints>false</useDomainConstraints>
<use>0</use>
<logicalDatatype>LOGDT024</logicalDatatype>
<domain>66D61FA5-E6FC-8A0C-8A86-570E5077EE6C</domain>
<delegate>85DC063C-7C1C-DC9C-49F2-C56F40C0F8E8</delegate>
<previousColumn>false</previousColumn>
<associations>
<colAssociation fkAssociation="E7ADC9B5-EE2F-22DA-21BC-79EEF483EE71" referredColumn="85DC063C-7C1C-DC9C-49F2-C56F40C0F8E8"/>
</associations>
</Column>
<Column class="oracle.dbtools.crest.model.design.relational.Column" name="AGR_ID" id="EA3C65B3-25A8-FB2B-0E83-32CCF773AB29">
<createdBy>Scott</createdBy>
<createdTime>2011-10-26 10:37:49 UTC</createdTime>
<generatorID>7012B952-D88E-D87A-2293-1DE8EEE8864A</generatorID>
<ownerDesignName>Population Statistics Reference</ownerDesignName>
<nullsAllowed>true</nullsAllowed>
<useDomainConstraints>false</useDomainConstraints>
<use>0</use>
<logicalDatatype>LOGDT011</logicalDatatype>
<domain>7902D946-5C37-B380-3248-80191020E6EF</domain>
<delegate>0F169528-51D5-2E96-A990-8BD3EEFC0CFE</delegate>
<previousColumn>false</previousColumn>
<associations>
<colAssociation fkAssociation="9EA24DFD-571F-BCEC-B9BB-5F8EA2C8266B" referredColumn="E887FD2B-4164-C0ED-B1AC-5A298B0AAA7E"/>
</associations>
</Column>
<Column class="oracle.dbtools.crest.model.design.relational.Column" name="VALUE" id="97461C8E-E88E-2C29-6540-88CDB441BE21">
<createdBy>Scott</createdBy>
<createdTime>2011-10-26 10:37:49 UTC</createdTime>
<generatorID>B5CA399E-2628-EDF5-57D7-DA046D21C6FC</generatorID>
<ownerDesignName>Population Statistics Reference</ownerDesignName>
<constraintName>x</constraintName>
<use>0</use>
<logicalDatatype>LOGDT011</logicalDatatype>
<domain>63D589BF-9681-517D-9347-14CEE8D4D12B</domain>
<previousColumn>false</previousColumn>
</Column>
<Column class="oracle.dbtools.crest.model.design.relational.Column" name="ITM_ID" id="CA1A4C22-EC2B-E587-9E08-010ACB965070">
<createdBy>Scott</createdBy>
<createdTime>2011-12-08 07:38:08 UTC</createdTime>
<ownerDesignName>Population Statistics Reference</ownerDesignName>
<nullsAllowed>true</nullsAllowed>
<useDomainConstraints>false</useDomainConstraints>
<use>1</use>
<logicalDatatype>LOGDT011</logicalDatatype>
<delegate>2A6FD6C7-5546-B8AB-418B-2F3780605451</delegate>
<associations>
<colAssociation fkAssociation="32927A11-2E1B-3413-9C89-7CBBA0FA04BD" referredColumn="2A6FD6C7-5546-B8AB-418B-2F3780605451"/>
</associations>
</Column>
<Column class="oracle.dbtools.crest.model.design.relational.Column" name="UPDATE_TIMESTAMP" id="65CB4B3B-AC01-9609-A5CB-9541D74B798D">
<createdBy>Scott</createdBy>
<createdTime>2012-03-27 12:53:33 UTC</createdTime>
<ownerDesignName>Population Statistics Reference</ownerDesignName>
<defaultValue>systimestamp</defaultValue>
<use>0</use>
<logicalDatatype>LOGDT047</logicalDatatype>
<domain>E2B7E866-FAE8-A49C-207C-DA7D30D89715</domain>
<autoIncrementCycle>false</autoIncrementCycle>
</Column>
<Column class="oracle.dbtools.crest.model.design.relational.Column" name="UPDATE_USERID" id="C62E246A-F6CE-8617-5E23-8212F6C4EA9E">
<createdBy>Scott</createdBy>
<createdTime>2012-03-27 12:53:33 UTC</createdTime>
<ownerDesignName>Population Statistics Reference</ownerDesignName>
<defaultValue>nvl(sys_context(&apos;PSR&apos;, &apos;USERID&apos;), &apos;*&apos; || user)</defaultValue>
<use>0</use>
<logicalDatatype>LOGDT024</logicalDatatype>
<domain>1B3AF57E-8DA8-A2E2-DAC5-0A66F68D2FBE</domain>
<autoIncrementCycle>false</autoIncrementCycle>
</Column>
<Column class="oracle.dbtools.crest.model.design.relational.Column" name="VERSION_NBR" id="C4B3C1A3-E56E-9135-C4F4-EC30DB5AC759">
<createdBy>Scott</createdBy>
<createdTime>2012-03-27 10:26:37 UTC</createdTime>
<ownerDesignName>Population Statistics Reference</ownerDesignName>
<defaultValue>1</defaultValue>
<use>0</use>
<logicalDatatype>LOGDT011</logicalDatatype>
<domain>C708458E-1701-E597-89A0-AB5975C13369</domain>
<autoIncrementCycle>false</autoIncrementCycle>
</Column>
</columns>
<indexes>
<ind_PK_UK class="oracle.dbtools.crest.model.design.relational.Index" id="016AE230-5C17-8B81-A92D-F2541F4CA97D" name="PK_STC">
<createdBy>Scott</createdBy>
<createdTime>2011-10-26 10:37:49 UTC</createdTime>
<generatorID>B61CAF90-A58C-AFB7-7887-5E3ED482488B</generatorID>
<ownerDesignName>Population Statistics Reference</ownerDesignName>
<pk>true</pk>
<indexState>Primary Constraint</indexState>
<indexColumnUsage>
<colUsage columnID="9DBA208D-CE95-1051-9F37-5BC61B6244C2"/>
</indexColumnUsage>
</ind_PK_UK>
<ind_PK_UK class="oracle.dbtools.crest.model.design.relational.Index" id="417DDAB6-CF3F-CB59-4372-3592E9E4E798" name="UK_STC">
<createdBy>Scott</createdBy>
<createdTime>2011-10-26 14:26:38 UTC</createdTime>
<ownerDesignName>Population Statistics Reference</ownerDesignName>
<indexState>Unique Constraint</indexState>
<indexColumnUsage>
<colUsage columnID="29CC72C1-8AEF-0D91-DDA5-FEF62A8456E7"/>
<colUsage columnID="7F16941E-0450-0982-F034-DF334E5BB70B"/>
<colUsage columnID="94054760-D809-F88B-4EEE-0DACCFC1F534"/>
<colUsage columnID="12403EFF-B965-DC85-DF84-4FD6950E185D"/>
<colUsage columnID="EA3C65B3-25A8-FB2B-0E83-32CCF773AB29"/>
</indexColumnUsage>
</ind_PK_UK>
<ind_PK_UK class="oracle.dbtools.crest.model.design.relational.Index" id="0CBCA6D2-74EE-76EB-DDB2-384C7AFDF914" name="UK_STC_ITM_ID">
<createdBy>Scott</createdBy>
<createdTime>2011-12-08 08:43:58 UTC</createdTime>
<ownerDesignName>Population Statistics Reference</ownerDesignName>
<indexState>Unique Constraint</indexState>
<indexColumnUsage>
<colUsage columnID="CA1A4C22-EC2B-E587-9E08-010ACB965070"/>
</indexColumnUsage>
</ind_PK_UK>
<ind_PK_UK class="oracle.dbtools.crest.model.design.relational.Index" id="CC7B5018-5761-D59B-D7FF-5A7A36C1DBF4" name="FK_STC_AGR">
<createdBy>Scott</createdBy>
<createdTime>2011-10-26 10:37:49 UTC</createdTime>
<generatorID>9E2BC500-F420-94A0-1AE5-6756FD449A11</generatorID>
<ownerDesignName>Population Statistics Reference</ownerDesignName>
<indexState>Foreign Key</indexState>
<indexColumnUsage>
<colUsage columnID="EA3C65B3-25A8-FB2B-0E83-32CCF773AB29"/>
</indexColumnUsage>
</ind_PK_UK>
<ind_PK_UK class="oracle.dbtools.crest.model.design.relational.Index" id="6098F9E0-A0E7-092B-86AE-1B51A9389942" name="FK_STC_STCT">
<createdBy>Scott</createdBy>
<createdTime>2011-10-26 10:37:49 UTC</createdTime>
<generatorID>C4A3AE96-0C50-53D7-98BF-868827D1D46F</generatorID>
<ownerDesignName>Population Statistics Reference</ownerDesignName>
<indexState>Foreign Key</indexState>
<indexColumnUsage>
<colUsage columnID="7F16941E-0450-0982-F034-DF334E5BB70B"/>
</indexColumnUsage>
</ind_PK_UK>
<ind_PK_UK class="oracle.dbtools.crest.model.design.relational.Index" id="A184B3B4-7AD5-735A-FCAC-8330348455A5" name="FK_STC_ITM">
<createdBy>Scott</createdBy>
<createdTime>2011-12-08 07:38:08 UTC</createdTime>
<ownerDesignName>Population Statistics Reference</ownerDesignName>
<indexState>Foreign Key</indexState>
<indexColumnUsage>
<colUsage columnID="CA1A4C22-EC2B-E587-9E08-010ACB965070"/>
</indexColumnUsage>
</ind_PK_UK>
<ind_PK_UK class="oracle.dbtools.crest.model.design.relational.Index" id="2EB02C21-1B7E-E4E2-49AD-0A0ECE12CB97" name="FK_STC_PER">
<createdBy>Scott</createdBy>
<createdTime>2012-03-29 14:16:41 UTC</createdTime>
<ownerDesignName>Population Statistics Reference</ownerDesignName>
<indexState>Foreign Key</indexState>
<indexColumnUsage>
<colUsage columnID="94054760-D809-F88B-4EEE-0DACCFC1F534"/>
</indexColumnUsage>
</ind_PK_UK>
<ind_PK_UK class="oracle.dbtools.crest.model.design.relational.Index" id="FA4BE08A-1B63-C128-9559-D1FAC6AD6E1A" name="FK_STC_SEX">
<createdBy>Scott</createdBy>
<createdTime>2012-04-10 12:19:52 UTC</createdTime>
<ownerDesignName>Population Statistics Reference</ownerDesignName>
<indexState>Foreign Key</indexState>
<indexColumnUsage>
<colUsage columnID="12403EFF-B965-DC85-DF84-4FD6950E185D"/>
</indexColumnUsage>
</ind_PK_UK>
<ind_PK_UK class="oracle.dbtools.crest.model.design.relational.Index" id="57FC7734-BF21-AF72-BEBE-CF6ADA59FD73" name="FK_STC_PSG">
<createdBy>Scott</createdBy>
<createdTime>2012-09-05 15:07:25 UTC</createdTime>
<ownerDesignName>Population Statistics Reference</ownerDesignName>
<indexState>Foreign Key</indexState>
<indexColumnUsage>
<colUsage columnID="29CC72C1-8AEF-0D91-DDA5-FEF62A8456E7"/>
</indexColumnUsage>
</ind_PK_UK>
</indexes>
</Table>